xlsindy/__init__.py
xlsindy/catalog.py
xlsindy/dynamics_modeling.py
xlsindy/euler_lagrange.py
xlsindy/logger.py
xlsindy/optimization.py
xlsindy/render.py
xlsindy/result_formatting.py
xlsindy/simulation.py
xlsindy/sindy_utils.py
xlsindy/symbolic_util.py
xlsindy/utils.py
xlsindy/catalog_base/__init__.py
xlsindy/catalog_base/_classical.py
xlsindy/catalog_base/_external_forces.py
xlsindy/catalog_base/_lagrangian.py
py_xl_sindy-2.2.1.dist-info/METADATA
py_xl_sindy-2.2.1.dist-info/WHEEL
py_xl_sindy-2.2.1.dist-info/licenses/LICENSE
py_xl_sindy-2.2.1.dist-info/RECORD
