Metadata-Version: 2.4
Name: py-xl-sindy
Version: 2.2.1
Summary: The repository of the py-xl-sindy python package
License-File: LICENSE
Requires-Python: >=3.12
Requires-Dist: cvxpy>=1.7.3
Requires-Dist: jax>=0.5.3
Requires-Dist: matplotlib>=3.10.6
Requires-Dist: networkx>=3.4.2
Requires-Dist: numpy>=1.26.4
Requires-Dist: pydantic>=2.12.5
Requires-Dist: scikit-learn>=1.7.2
Requires-Dist: scipy>=1.15.3
Requires-Dist: sympy>=1.14.0
Requires-Dist: tqdm>=4.67.1
Provides-Extra: gpu
Requires-Dist: cucim-cu12>=25.8.0; extra == 'gpu'
Requires-Dist: cudf-cu12>=24.4.1; extra == 'gpu'
Requires-Dist: cugraph-cu12>=24.4.0; extra == 'gpu'
Requires-Dist: cuml-cu12>=24.4.0; extra == 'gpu'
Requires-Dist: cuvs-cu12>=24.4.0; extra == 'gpu'
Requires-Dist: cuxfilter-cu12>=24.4.1; extra == 'gpu'
Requires-Dist: dask-cudf-cu12>=24.4.1; extra == 'gpu'
Requires-Dist: jax[cuda12]>=0.5.3; extra == 'gpu'
Requires-Dist: nx-cugraph-cu12>=24.4.0; extra == 'gpu'
Requires-Dist: pylibraft-cu12>=24.4.0; extra == 'gpu'
Requires-Dist: raft-dask-cu12>=24.4.0; extra == 'gpu'
